dorsa_logger/__init__.py
dorsa_logger/dorsa_logger.py
dorsa_logger-1.0.0.dist-info/LICENSE.txt
dorsa_logger-1.0.0.dist-info/METADATA
dorsa_logger-1.0.0.dist-info/WHEEL
dorsa_logger-1.0.0.dist-info/top_level.txt
dorsa_logger-1.0.0.dist-info/RECORD
