Metadata-Version: 2.1
Name: dorsa-logger
Version: 1.0.0
Summary: Dorsa Logger Module
Home-page: https://github.com/DORSA-co/dorsa_logger
Author: Dorsa-co
Author-email: info@dorsa-co.ir
License: Apache License 2.0
Project-URL: Bug Tracker, https://github.com/DORSA-co/dorsa_logger/issues
Keywords: dorsa_logger
Classifier: Intended Audience :: Developers
Classifier: Topic :: Software Development :: Documentation
Classifier: License :: OSI Approved :: Apache Software License
Classifier: Programming Language :: Python :: 3
License-File: LICENSE.txt
Requires-Dist: persiantools
